crud/__init__.py
crud/apps.py
crud/__pycache__/__init__.cpython-36.pyc
crud/__pycache__/__init__.cpython-37.pyc
crud/app_template/__init__.py-tpl
crud/app_template/apps.py-tpl
crud/app_template/tests.py-tpl
crud/app_template/admin/__init__.py-tpl
crud/app_template/admin/admin.py-tpl
crud/app_template/forms/__init__.py-tpl
crud/app_template/locale/ja/LC_MESSAGES/django.mo
crud/app_template/locale/ja/LC_MESSAGES/django.po
crud/app_template/migrations/__init__.py-tpl
crud/app_template/models/__init__.py-tpl
crud/app_template/models/snake_case_model_name.py-tpl
crud/app_template/templates/app_name/base.html
crud/app_template/templates/app_name/create.html
crud/app_template/templates/app_name/delete.html
crud/app_template/templates/app_name/detail.html
crud/app_template/templates/app_name/list.html
crud/app_template/templates/app_name/update.html
crud/app_template/urls/__init__.py-tpl
crud/app_template/views/__init__.py-tpl
crud/app_template/views/create.py-tpl
crud/app_template/views/delete.py-tpl
crud/app_template/views/detail.py-tpl
crud/app_template/views/list.py-tpl
crud/app_template/views/update.py-tpl
crud/management/templates.py
crud/management/__pycache__/templates.cpython-36.pyc
crud/management/__pycache__/templates.cpython-37.pyc
crud/management/commands/startcrud.py
crud/management/commands/__pycache__/startcrud.cpython-36.pyc
crud/management/commands/__pycache__/startcrud.cpython-37.pyc
crud/user_template/__init__.py-tpl
crud/user_template/apps.py-tpl
crud/user_template/tests.py-tpl
crud/user_template/admin/__init__.py-tpl
crud/user_template/admin/admin.py-tpl
crud/user_template/forms/__init__.py-tpl
crud/user_template/locale/ja/LC_MESSAGES/django.mo
crud/user_template/locale/ja/LC_MESSAGES/django.po
crud/user_template/migrations/__init__.py-tpl
crud/user_template/models/__init__.py-tpl
crud/user_template/models/snake_case_model_name.py-tpl
crud/user_template/templates/user_name/base.html
crud/user_template/templates/user_name/create.html
django_crud_app-0.2.3.dist-info/METADATA
django_crud_app-0.2.3.dist-info/WHEEL
django_crud_app-0.2.3.dist-info/top_level.txt
django_crud_app-0.2.3.dist-info/RECORD
